[
    {
        "source": "&lt;a href=&quot;http://www.ntdtv.com&quot; rel=&quot;nofollow&quot;&gt;NTDTV News&lt;/a&gt;",
        "from_user": "SoundOfHopeCa",
        "created_at": "Tue, 10 Apr 2012 22:17:15 +0000",
        "status_url": "http://twitter.com/SoundOfHopeCa/statuses/189839489005387776",
        "entities_str": "{\"urls\":[{\"expanded_url\":\"http://sohcradio.com/b5/2012/04/10/Art47782.html\",\"indices\":[94,114],\"display_url\":\"sohcradio.com/b5/2012/04/10/\\u2026\",\"url\":\"http://t.co/tOy5KAvT\"}],\"hashtags\":[],\"user_mentions\":[]}",
        "profile_image_url": "http://a0.twimg.com/profile_images/1807581124/English-SOH_logo_copy_normal.jpg",
        "iso_language_code": "zh",
        "geo_coordinates": null,
        "time": "10/04/2012 22:17:15",
        "text": "华邮：薄熙来被除名 妻被捕 周永康未露面   当地时间4月10日，美国华府的《华盛顿邮报》引述新华社周二的报导说，中共宣布，薄熙来从政治局和中央委员会除名，并将被正式调查。其妻谷开来被控\nhttp://t.co/tOy5KAvT",
        "to_user": null,
        "id_str": 1.89839489005388e+17,
        "from_user_id_str": 484436480,
        "to_user_id_str": null
    },
    {
        "source": "&lt;a href=&quot;http://twitter.com/&quot;&gt;web&lt;/a&gt;",
        "from_user": "gjxk",
        "created_at": "Tue, 10 Apr 2012 22:16:30 +0000",
        "status_url": "http://twitter.com/gjxk/statuses/189839299880026113",
        "entities_str": "{\"urls\":[],\"hashtags\":[],\"user_mentions\":[]}",
        "profile_image_url": "http://a0.twimg.com/profile_images/1203579270/GJX_normal.jpg",
        "iso_language_code": "zh",
        "geo_coordinates": null,
        "time": "10/04/2012 22:16:30",
        "text": "薄熙来现在后悔莫及了吧？想当初还不如一不做二不休，也来个全副武装手持冲锋枪，杀气腾腾地宣布独立，说不定倒能铤而走险地觅得一条活路。现在只能成为砧板上的鱼肉了。",
        "to_user": null,
        "id_str": 1.8983929988002598e+17,
        "from_user_id_str": 110159288,
        "to_user_id_str": null
    },
    {
        "source": "&lt;a href=&quot;http://www.shapeservices.com/en/products/details.php?product=im&amp;platform=none&quot; rel=&quot;nofollow&quot;&gt;IM+&lt;/a&gt;",
        "from_user": "b2d",
        "created_at": "Tue, 10 Apr 2012 22:15:44 +0000",
        "status_url": "http://twitter.com/b2d/statuses/189839104274481152",
        "entities_str": "{\"urls\":[],\"hashtags\":[],\"user_mentions\":[]}",
        "profile_image_url": "http://a0.twimg.com/profile_images/81103926/379x388_normal.JPG",
        "iso_language_code": "zh",
        "geo_coordinates": null,
        "time": "10/04/2012 22:15:44",
        "text": "今天所有国内媒体头版头条都应是薄熙来被中央处理的消息。乌有之乡被关闭。现世报啊！其内幕睡上百女人、转移几亿资产、几条人命、属下叛国、其妻毒杀英国管家，曲折离奇堪比芝加哥黑帮片！这就是现实中的天朝政治斗争。",
        "to_user": null,
        "id_str": 1.8983910427448099e+17,
        "from_user_id_str": 21504622,
        "to_user_id_str": null
    },
    {
        "source": "&lt;a href=&quot;http://twitter.com/&quot;&gt;web&lt;/a&gt;",
        "from_user": "marycattle1223",
        "created_at": "Tue, 10 Apr 2012 22:15:04 +0000",
        "status_url": "http://twitter.com/marycattle1223/statuses/189838938213584897",
        "entities_str": "{\"urls\":[],\"hashtags\":[],\"user_mentions\":[]}",
        "profile_image_url": "http://a0.twimg.com/sticky/default_profile_images/default_profile_3_normal.png",
        "iso_language_code": "zh",
        "geo_coordinates": null,
        "time": "10/04/2012 22:15:04",
        "text": "英国公民尼尔伍德被谷开来和薄熙来的家丁杀了，这事儿是被王立军从美国领馆里带出来的，如果他没去呢？事情要隐瞒多久？死在他们手上的中国人，又有多少？妻室和家丁杀人，仅仅一个“严重违纪”就能解决？明明在国际上已经传出臭名，却还说什么依法治国的决心？呵呵 下一个呢？",
        "to_user": null,
        "id_str": 1.8983893821358499e+17,
        "from_user_id_str": 291758386,
        "to_user_id_str": null
    },
    {
        "source": "&lt;a href=&quot;http://wbto.cn/&quot; rel=&quot;nofollow&quot;&gt;享拍微博通&lt;/a&gt;",
        "from_user": "aigo1949",
        "created_at": "Tue, 10 Apr 2012 22:13:32 +0000",
        "status_url": "http://twitter.com/aigo1949/statuses/189838550039134208",
        "entities_str": "{\"urls\":[{\"expanded_url\":\"http://url.cn/0lMCoR\",\"indices\":[71,91],\"display_url\":\"url.cn/0lMCoR\",\"url\":\"http://t.co/G9tjMkyG\"}],\"hashtags\":[],\"user_mentions\":[]}",
        "profile_image_url": "http://a0.twimg.com/profile_images/1946966004/QQ__20120325014330_normal.png",
        "iso_language_code": "zh",
        "geo_coordinates": null,
        "time": "10/04/2012 22:13:32",
        "text": "@腾讯新闻:中央电视台消息，中共中央决定对薄熙来严重违纪问题立案调查，停止其中央政治局委员职务。薄熙来妻子薄谷开来涉嫌杀害英国商人尼尔·伍德。http://t.co/G9tjMkyG  //",
        "to_user": null,
        "id_str": 1.8983855003913398e+17,
        "from_user_id_str": 535544572,
        "to_user_id_str": null
    },
    {
        "source": "&lt;a href=&quot;http://twitter.com/&quot;&gt;web&lt;/a&gt;",
        "from_user": "IWJ_KB_SPTR",
        "created_at": "Tue, 10 Apr 2012 22:12:37 +0000",
        "status_url": "http://twitter.com/IWJ_KB_SPTR/statuses/189838320912711680",
        "entities_str": "{\"urls\":[{\"expanded_url\":\"http://news.boxun.com/news/gb/china/2012/04/201204110100.shtml\",\"indices\":[41,61],\"display_url\":\"news.boxun.com/news/gb/china/\\u2026\",\"url\":\"http://t.co/euJdCCcr\"}],\"hashtags\":[],\"user_mentions\":[{\"id\":129237555,\"name\":\"丁丁猫\",\"indices\":[3,10],\"screen_name\":\"avb001\",\"id_str\":\"129237555\"}]}",
        "profile_image_url": "http://a0.twimg.com/sticky/default_profile_images/default_profile_2_normal.png",
        "iso_language_code": "zh",
        "geo_coordinates": null,
        "time": "10/04/2012 22:12:37",
        "text": "RT @avb001: 博讯独家爆料来了！：薄熙来夫妇涉害多人 谷开来恐性命不保 http://t.co/euJdCCcr",
        "to_user": null,
        "id_str": 1.89838320912712e+17,
        "from_user_id_str": 252810959,
        "to_user_id_str": null
    },
    {
        "source": "&lt;a href=&quot;http://www.google.com/&quot; rel=&quot;nofollow&quot;&gt;Google&lt;/a&gt;",
        "from_user": "kanzhongguonews",
        "created_at": "Tue, 10 Apr 2012 22:10:25 +0000",
        "status_url": "http://twitter.com/kanzhongguonews/statuses/189837768598355968",
        "entities_str": "{\"urls\":[{\"expanded_url\":\"http://goo.gl/fb/93lMJ\",\"indices\":[95,115],\"display_url\":\"goo.gl/fb/93lMJ\",\"url\":\"http://t.co/Mh0pzrw1\"}],\"hashtags\":[],\"user_mentions\":[]}",
        "profile_image_url": "http://a0.twimg.com/profile_images/1741995871/default_normal.jpg",
        "iso_language_code": "zh",
        "geo_coordinates": null,
        "time": "10/04/2012 22:10:25",
        "text": "薄熙来垮台—中共内斗加剧？: 由于涉嫌严重违纪，上个月刚被免去重庆市委书记的薄熙来的最后两个重要职务，中共中央政治局委员和中央委员，也被停止。中纪委已经对他立案调查。与此同时，他的妻子谷… http://t.co/Mh0pzrw1",
        "to_user": null,
        "id_str": 1.89837768598356e+17,
        "from_user_id_str": 117590362,
        "to_user_id_str": null
    },
    {
        "source": "&lt;a href=&quot;http://www.google.com/&quot; rel=&quot;nofollow&quot;&gt;Google&lt;/a&gt;",
        "from_user": "kanzhongguonews",
        "created_at": "Tue, 10 Apr 2012 22:10:25 +0000",
        "status_url": "http://twitter.com/kanzhongguonews/statuses/189837767184883716",
        "entities_str": "{\"urls\":[{\"expanded_url\":\"http://goo.gl/fb/lxhP2\",\"indices\":[94,114],\"display_url\":\"goo.gl/fb/lxhP2\",\"url\":\"http://t.co/mdJDiRD6\"}],\"hashtags\":[],\"user_mentions\":[]}",
        "profile_image_url": "http://a0.twimg.com/profile_images/1741995871/default_normal.jpg",
        "iso_language_code": "zh",
        "geo_coordinates": null,
        "time": "10/04/2012 22:10:25",
        "text": "世界媒体看中国：薄督与美国(图): 薄熙来春风得意时资料照 “薄督”是中国网民给前中国共产党重庆市委书记薄熙来的外号。 4月10星期二，中国官方权威通讯社新华社发表电讯说，“鉴于薄熙来… http://t.co/mdJDiRD6",
        "to_user": null,
        "id_str": 1.89837767184884e+17,
        "from_user_id_str": 117590362,
        "to_user_id_str": null
    },
    {
        "source": "&lt;a href=&quot;http://www.google.com/&quot; rel=&quot;nofollow&quot;&gt;Google&lt;/a&gt;",
        "from_user": "kanzhongguonews",
        "created_at": "Tue, 10 Apr 2012 22:10:25 +0000",
        "status_url": "http://twitter.com/kanzhongguonews/statuses/189837765804965888",
        "entities_str": "{\"urls\":[{\"expanded_url\":\"http://goo.gl/fb/MKZMm\",\"indices\":[95,115],\"display_url\":\"goo.gl/fb/MKZMm\",\"url\":\"http://t.co/qYC8qNK3\"}],\"hashtags\":[],\"user_mentions\":[]}",
        "profile_image_url": "http://a0.twimg.com/profile_images/1741995871/default_normal.jpg",
        "iso_language_code": "zh",
        "geo_coordinates": null,
        "time": "10/04/2012 22:10:25",
        "text": "薄熙来下马不能与中国改革划等号(图): 新华社证实薄熙来涉嫌严重违纪的消息，以及薄妻子的故意杀人嫌疑。观察人士认为，薄的落马可能代表中国避免了倒退回文革的危险，但并不意味着会出现突破性的… http://t.co/qYC8qNK3",
        "to_user": null,
        "id_str": 1.8983776580496598e+17,
        "from_user_id_str": 117590362,
        "to_user_id_str": null
    },
    {
        "source": "&lt;a href=&quot;http://www.google.com/&quot; rel=&quot;nofollow&quot;&gt;Google&lt;/a&gt;",
        "from_user": "kanzhongguonews",
        "created_at": "Tue, 10 Apr 2012 22:10:24 +0000",
        "status_url": "http://twitter.com/kanzhongguonews/statuses/189837763682635776",
        "entities_str": "{\"urls\":[{\"expanded_url\":\"http://goo.gl/fb/V8JHl\",\"indices\":[94,114],\"display_url\":\"goo.gl/fb/V8JHl\",\"url\":\"http://t.co/TY2ktREz\"}],\"hashtags\":[],\"user_mentions\":[]}",
        "profile_image_url": "http://a0.twimg.com/profile_images/1741995871/default_normal.jpg",
        "iso_language_code": "zh",
        "geo_coordinates": null,
        "time": "10/04/2012 22:10:24",
        "text": "汪北稷：小薄彻底倒台 中共何时了断: 4月10日，中共独裁政权的所谓中央，终于发出裁决，将中共的高层领导薄熙来赶出了中央领导圈子，赶到了秦城监狱的门口。 可见本人在3月23日看中国网站… http://t.co/TY2ktREz",
        "to_user": null,
        "id_str": 1.89837763682636e+17,
        "from_user_id_str": 117590362,
        "to_user_id_str": null
    },
    {
        "source": "&lt;a href=&quot;http://ifttt.com&quot; rel=&quot;nofollow&quot;&gt;ifttt&lt;/a&gt;",
        "from_user": "preachercn",
        "created_at": "Tue, 10 Apr 2012 22:09:10 +0000",
        "status_url": "http://twitter.com/preachercn/statuses/189837454075904001",
        "entities_str": "{\"urls\":[{\"expanded_url\":\"http://bit.ly/HGPsgl\",\"indices\":[136,156],\"display_url\":\"bit.ly/HGPsgl\",\"url\":\"http://t.co/IIa5OWlV\"}],\"hashtags\":[{\"text\":\"yizhe\",\"indices\":[16,22]}],\"user_mentions\":[{\"id\":95225426,\"name\":\"Yizhe\",\"indices\":[3,14],\"screen_name\":\"xiaomi2020\",\"id_str\":\"95225426\"}]}",
        "profile_image_url": "http://a0.twimg.com/profile_images/773666550/____normal.jpg",
        "iso_language_code": "zh",
        "geo_coordinates": null,
        "time": "10/04/2012 22:09:10",
        "text": "RT @xiaomi2020: #yizhe 路透社独家：中国暂停薄熙来的党内领导职务 核心提示：路透社抢在cctv之前发布薄熙来被开除出中共中央委员会和中央政治局的消息。   原文：Exclusive: China suspends Bo Xilai from ... http://t.co/IIa5OWlV",
        "to_user": null,
        "id_str": 1.89837454075904e+17,
        "from_user_id_str": 125548542,
        "to_user_id_str": null
    }
]